pyforms/__init__.py
pyforms/basewidget.py
pyforms/controls.py
pyforms/dialogs.py
pyforms/settings.py
pyforms_gui/__init__.py
pyforms_gui/allcontrols.py
pyforms_gui/appmanager.py
pyforms_gui/basewidget.py
pyforms_gui/organizers.py
pyforms_gui/resources_settings.py
pyforms_gui/settings.py
pyforms_gui/controls/__init__.py
pyforms_gui/controls/button.ui
pyforms_gui/controls/checkbox.ui
pyforms_gui/controls/code_editor.ui
pyforms_gui/controls/control_base.py
pyforms_gui/controls/control_boundingslider.py
pyforms_gui/controls/control_button.py
pyforms_gui/controls/control_checkbox.py
pyforms_gui/controls/control_checkboxlist.py
pyforms_gui/controls/control_codeeditor.py
pyforms_gui/controls/control_combo.py
pyforms_gui/controls/control_dir.py
pyforms_gui/controls/control_dockwidget.py
pyforms_gui/controls/control_emptywidget.py
pyforms_gui/controls/control_file.py
pyforms_gui/controls/control_filestree.py
pyforms_gui/controls/control_image.py
pyforms_gui/controls/control_label.py
pyforms_gui/controls/control_list.py
pyforms_gui/controls/control_matplotlib.py
pyforms_gui/controls/control_mdiarea.py
pyforms_gui/controls/control_number.py
pyforms_gui/controls/control_opengl.py
pyforms_gui/controls/control_password.py
pyforms_gui/controls/control_progress.py
pyforms_gui/controls/control_slider.py
pyforms_gui/controls/control_tableview.py
pyforms_gui/controls/control_text.py
pyforms_gui/controls/control_textarea.py
pyforms_gui/controls/control_toolbox.py
pyforms_gui/controls/control_toolbutton.py
pyforms_gui/controls/control_tree.py
pyforms_gui/controls/control_treeview.py
pyforms_gui/controls/control_visvis.py
pyforms_gui/controls/control_visvisvolume.py
pyforms_gui/controls/control_web.py
pyforms_gui/controls/fileInput.ui
pyforms_gui/controls/image.ui
pyforms_gui/controls/label.ui
pyforms_gui/controls/list.ui
pyforms_gui/controls/number.ui
pyforms_gui/controls/progressInput.ui
pyforms_gui/controls/sliderInput.ui
pyforms_gui/controls/table-view.ui
PyForms_GUI_shaliulab-4.905.157.dist-info/METADATA
PyForms_GUI_shaliulab-4.905.157.dist-info/WHEEL
PyForms_GUI_shaliulab-4.905.157.dist-info/top_level.txt
PyForms_GUI_shaliulab-4.905.157.dist-info/RECORD
